gmailarchiver/__init__.py
gmailarchiver/__main__.py
gmailarchiver/_version.py
gmailarchiver/cli/ARCHITECTURE.md
gmailarchiver/cli/README.md
gmailarchiver/cli/__init__.py
gmailarchiver/cli/_output_search.py
gmailarchiver/cli/adapters.py
gmailarchiver/cli/command_context.py
gmailarchiver/cli/consolidate.py
gmailarchiver/cli/dedupe.py
gmailarchiver/cli/doctor.py
gmailarchiver/cli/main.py
gmailarchiver/cli/migrate.py
gmailarchiver/cli/output.py
gmailarchiver/cli/repair.py
gmailarchiver/cli/schedule.py
gmailarchiver/cli/ui_builder.py
gmailarchiver/cli/verify.py
gmailarchiver/cli/widgets.py
gmailarchiver/cli/commands/archive.py
gmailarchiver/cli/commands/consolidate.py
gmailarchiver/cli/commands/dedupe.py
gmailarchiver/cli/commands/doctor.py
gmailarchiver/cli/commands/import_.py
gmailarchiver/cli/commands/migrate.py
gmailarchiver/cli/commands/repair.py
gmailarchiver/cli/commands/schedule.py
gmailarchiver/cli/commands/search.py
gmailarchiver/cli/commands/status.py
gmailarchiver/cli/commands/validate.py
gmailarchiver/cli/commands/verify.py
gmailarchiver/cli/ui/ARCHITECTURE.md
gmailarchiver/cli/ui/__init__.py
gmailarchiver/cli/ui/adapters.py
gmailarchiver/cli/ui/builder.py
gmailarchiver/cli/ui/protocols.py
gmailarchiver/cli/ui/widgets/__init__.py
gmailarchiver/cli/ui/widgets/errors.py
gmailarchiver/cli/ui/widgets/log_window.py
gmailarchiver/cli/ui/widgets/progress.py
gmailarchiver/cli/ui/widgets/progress_bar.py
gmailarchiver/cli/ui/widgets/report_card.py
gmailarchiver/cli/ui/widgets/suggestions.py
gmailarchiver/cli/ui/widgets/table.py
gmailarchiver/cli/ui/widgets/task.py
gmailarchiver/cli/ui/widgets/validation.py
gmailarchiver/cli/ui/widgets/workflow_progress.py
gmailarchiver/connectors/ARCHITECTURE.md
gmailarchiver/connectors/README.md
gmailarchiver/connectors/__init__.py
gmailarchiver/connectors/auth.py
gmailarchiver/connectors/gmail_client.py
gmailarchiver/connectors/platform_scheduler.py
gmailarchiver/connectors/rate_limiter.py
gmail_archiver_cli-1.5.2.dist-info/METADATA
gmail_archiver_cli-1.5.2.dist-info/WHEEL
gmail_archiver_cli-1.5.2.dist-info/entry_points.txt
gmail_archiver_cli-1.5.2.dist-info/licenses/LICENSE
gmail_archiver_cli-1.5.2.dist-info/RECORD
