Metadata-Version: 2.4
Name: gmail-archiver-cli
Version: 1.5.2
Summary: A CLI tool to archive old Gmail messages to local mbox files with validation and safe deletion
Project-URL: Homepage, https://github.com/tumma72/GMailArchiver
Project-URL: Documentation, https://github.com/tumma72/GMailArchiver#readme
Project-URL: Repository, https://github.com/tumma72/GMailArchiver
Project-URL: Bug Tracker, https://github.com/tumma72/GMailArchiver/issues
Project-URL: Changelog, https://github.com/tumma72/GMailArchiver/blob/main/CHANGELOG.md
Project-URL: Release Notes, https://github.com/tumma72/GMailArchiver/releases
Author: GMailArchiver Contributors
Maintainer: GMailArchiver Contributors
License: Apache-2.0
License-File: LICENSE
Keywords: archive,backup,cli,email,gmail,mbox
Classifier: Development Status :: 5 - Production/Stable
Classifier: Environment :: Console
Classifier: Intended Audience :: End Users/Desktop
Classifier: License :: OSI Approved :: Apache Software License
Classifier: Operating System :: OS Independent
Classifier: Programming Language :: Python :: 3
Classifier: Programming Language :: Python :: 3.14
Classifier: Topic :: Communications :: Email
Classifier: Topic :: System :: Archiving
Classifier: Topic :: Utilities
Requires-Python: >=3.14
Requires-Dist: aiofiles>=25.1.0
Requires-Dist: aiosqlite>=0.21.0
Requires-Dist: google-api-python-client>=2.100.0
Requires-Dist: google-auth-httplib2>=0.1.1
Requires-Dist: google-auth-oauthlib>=1.1.0
Requires-Dist: google-auth>=2.23.0
Requires-Dist: httpx[http2]>=0.28.1
Requires-Dist: python-dateutil>=2.8.2
Requires-Dist: questionary>=2.0.0
Requires-Dist: rich>=13.0.0
Requires-Dist: typer>=0.9.0
